massivetoollib/__init__.py
massivetoollib/_easyframe.py
massivetoollib/ang.py
massivetoollib/numconvert.py
massivetoollib-0.0.4.dist-info/LICENCE
massivetoollib-0.0.4.dist-info/METADATA
massivetoollib-0.0.4.dist-info/WHEEL
massivetoollib-0.0.4.dist-info/top_level.txt
massivetoollib-0.0.4.dist-info/RECORD
