Metadata-Version: 2.1
Name: massivetoollib
Version: 0.0.4
Summary: A pip generic developer package
Home-page: https://github.com/AngeloChDev
Author: AngeloChDev
Author-email: angeloch.dev@gmail.com
License: MIT
Keywords: Generic Developer Tools, Wedapp developer, Offline Software developer,Python package
Platform: UNKNOWN
Classifier: Programming Language :: Python
Classifier: Programming Language :: Python :: 3.10
Classifier: Development Status :: 4 - Beta
Classifier: Intended Audience :: Developers
Classifier: Natural Language :: English
Classifier: Operating System :: OS Independent
Classifier: Operating System :: Unix
Classifier: Operating System :: MacOS :: MacOS X
Classifier: Operating System :: Microsoft :: Windows
Classifier: Operating System :: POSIX
Classifier: Topic :: Software Development :: Libraries :: Python Modules
License-File: LICENCE
Requires-Dist: SQLAlchemy (>=1.4.28)
Requires-Dist: pandas
Requires-Dist: requests (>=2.25.0)
Requires-Dist: fastecdsa (>=2.2.1) ; platform_system != "Windows"
Requires-Dist: ecdsa (>=0.17) ; platform_system == "Windows"
Requires-Dist: numpy (==1.19.5) ; python_version < "3.8"
Requires-Dist: numpy (>=1.21.0) ; python_version >= "3.8"
